{"VideoResults": [{"frame": "valid0.jpg", "resultat": "Crash", "zone": 1, "date": "19-12-2019", "heure": "14h:38m:55s"},{"frame": "valid1.jpg", "resultat": "Crash", "zone": 1, "date": "19-12-2019", "heure": "14h:38m:55s"},{"frame": "valid10.jpg", "resultat": "Crash", "zone": 1, "date": "19-12-2019", "heure": "14h:38m:55s"},{"frame": "valid100.jpg", "resultat": "Crash", "zone": 1, "date": "19-12-2019", "heure": "14h:38m:55s"},{"frame": "valid101.jpg", "resultat": "Crash", "zone": 1, "date": "19-12-2019", "heure": "14h:38m:55s"},{"frame": "valid102.jpg", "resultat": "Crash", "zone": 1, "date": "19-12-2019", "heure": "14h:38m:55s"},{"frame": "valid103.jpg", "resultat": "Crash", "zone": 1, "date": "19-12-2019", "heure": "14h:38m:55s"},{"frame": "valid104.jpg", "resultat": "Crash", "zone": 1, "date": "19-12-2019", "heure": "14h:38m:55s"},{"frame": "valid105.jpg", "resultat": "Crash", "zone": 1, "date": "19-12-2019", "heure": "14h:38m:55s"},{"frame": "valid106.jpg", "resultat": "Crash", "zone": 1, "date": "19-12-2019", "heure": "14h:38m:55s"},{"frame": "valid107.jpg", "resultat": "Without Crash", "zone": 1, "date": "19-12-2019", "heure": "14h:38m:55s"},{"frame": "valid108.jpg", "resultat": "Crash", "zone": 1, "date": "19-12-2019", "heure": "14h:38m:55s"},{"frame": "valid109.jpg", "resultat": "Crash", "zone": 1, "date": "19-12-2019", "heure": "14h:38m:55s"},{"frame": "valid11.jpg", "resultat": "Crash", "zone": 1, "date": "19-12-2019", "heure": "14h:38m:55s"},{"frame": "valid110.jpg", "resultat": "Without Crash", "zone": 1, "date": "19-12-2019", "heure": "14h:38m:55s"},{"frame": "valid111.jpg", "resultat": "Crash", "zone": 1, "date": "19-12-2019", "heure": "14h:38m:55s"},{"frame": "valid112.jpg", "resultat": "Crash", "zone": 1, "date": "19-12-2019", "heure": "14h:38m:55s"},{"frame": "valid113.jpg", "resultat": "Without Crash", "zone": 1, "date": "19-12-2019", "heure": "14h:38m:55s"},{"frame": "valid114.jpg", "resultat": "Without Crash", "zone": 1, "date": "19-12-2019", "heure": "14h:38m:55s"},{"frame": "valid115.jpg", "resultat": "Crash", "zone": 1, "date": "19-12-2019", "heure": "14h:38m:55s"},{"frame": "valid116.jpg", "resultat": "Without Crash", "zone": 1, "date": "19-12-2019", "heure": "14h:38m:55s"},{"frame": "valid117.jpg", "resultat": "Without Crash", "zone": 1, "date": "19-12-2019", "heure": "14h:38m:55s"},{"frame": "valid118.jpg", "resultat": "Crash", "zone": 1, "date": "19-12-2019", "heure": "14h:38m:55s"},{"frame": "valid119.jpg", "resultat": "Crash", "zone": 1, "date": "19-12-2019", "heure": "14h:38m:55s"},{"frame": "valid12.jpg", "resultat": "Crash", "zone": 1, "date": "19-12-2019", "heure": "14h:38m:55s"},{"frame": "valid120.jpg", "resultat": "Crash", "zone": 1, "date": "19-12-2019", "heure": "14h:38m:55s"},{"frame": "valid121.jpg", "resultat": "Crash", "zone": 1, "date": "19-12-2019", "heure": "14h:38m:55s"},{"frame": "valid122.jpg", "resultat": "Crash", "zone": 1, "date": "19-12-2019", "heure": "14h:38m:55s"},{"frame": "valid123.jpg", "resultat": "Crash", "zone": 1, "date": "19-12-2019", "heure": "14h:38m:55s"},{"frame": "valid124.jpg", "resultat": "Crash", "zone": 1, "date": "19-12-2019", "heure": "14h:38m:55s"},{"frame": "valid125.jpg", "resultat": "Crash", "zone": 1, "date": "19-12-2019", "heure": "14h:38m:55s"},{"frame": "valid126.jpg", "resultat": "Crash", "zone": 1, "date": "19-12-2019", "heure": "14h:38m:55s"},{"frame": "valid127.jpg", "resultat": "Crash", "zone": 1, "date": "19-12-2019", "heure": "14h:38m:55s"},{"frame": "valid128.jpg", "resultat": "Crash", "zone": 1, "date": "19-12-2019", "heure": "14h:38m:55s"},{"frame": "valid129.jpg", "resultat": "Crash", "zone": 1, "date": "19-12-2019", "heure": "14h:38m:55s"},{"frame": "valid13.jpg", "resultat": "Crash", "zone": 1, "date": "19-12-2019", "heure": "14h:38m:55s"},{"frame": "valid130.jpg", "resultat": "Crash", "zone": 1, "date": "19-12-2019", "heure": "14h:38m:55s"},{"frame": "valid131.jpg", "resultat": "Crash", "zone": 1, "date": "19-12-2019", "heure": "14h:38m:55s"},{"frame": "valid132.jpg", "resultat": "Crash", "zone": 1, "date": "19-12-2019", "heure": "14h:38m:55s"},{"frame": "valid133.jpg", "resultat": "Crash", "zone": 1, "date": "19-12-2019", "heure": "14h:38m:55s"},{"frame": "valid134.jpg", "resultat": "Crash", "zone": 1, "date": "19-12-2019", "heure": "14h:38m:55s"},{"frame": "valid135.jpg", "resultat": "Crash", "zone": 1, "date": "19-12-2019", "heure": "14h:38m:55s"},{"frame": "valid136.jpg", "resultat": "Crash", "zone": 1, "date": "19-12-2019", "heure": "14h:38m:55s"},{"frame": "valid137.jpg", "resultat": "Crash", "zone": 1, "date": "19-12-2019", "heure": "14h:38m:55s"},{"frame": "valid138.jpg", "resultat": "Crash", "zone": 1, "date": "19-12-2019", "heure": "14h:38m:55s"},{"frame": "valid139.jpg", "resultat": "Crash", "zone": 1, "date": "19-12-2019", "heure": "14h:38m:55s"},{"frame": "valid14.jpg", "resultat": "Crash", "zone": 1, "date": "19-12-2019", "heure": "14h:38m:55s"},{"frame": "valid140.jpg", "resultat": "Crash", "zone": 1, "date": "19-12-2019", "heure": "14h:38m:55s"},{"frame": "valid141.jpg", "resultat": "Crash", "zone": 1, "date": "19-12-2019", "heure": "14h:38m:55s"},{"frame": "valid142.jpg", "resultat": "Crash", "zone": 1, "date": "19-12-2019", "heure": "14h:38m:55s"},{"frame": "valid143.jpg", "resultat": "Crash", "zone": 1, "date": "19-12-2019", "heure": "14h:38m:55s"},{"frame": "valid144.jpg", "resultat": "Crash", "zone": 1, "date": "19-12-2019", "heure": "14h:38m:55s"},{"frame": "valid145.jpg", "resultat": "Crash", "zone": 1, "date": "19-12-2019", "heure": "14h:38m:55s"},{"frame": "valid146.jpg", "resultat": "Crash", "zone": 1, "date": "19-12-2019", "heure": "14h:38m:55s"},{"frame": "valid147.jpg", "resultat": "Crash", "zone": 1, "date": "19-12-2019", "heure": "14h:38m:55s"},{"frame": "valid148.jpg", "resultat": "Without Crash", "zone": 1, "date": "19-12-2019", "heure": "14h:38m:55s"},{"frame": "valid149.jpg", "resultat": "Crash", "zone": 1, "date": "19-12-2019", "heure": "14h:38m:55s"},{"frame": "valid15.jpg", "resultat": "Crash", "zone": 1, "date": "19-12-2019", "heure": "14h:38m:55s"},{"frame": "valid150.jpg", "resultat": "Crash", "zone": 1, "date": "19-12-2019", "heure": "14h:38m:55s"},{"frame": "valid151.jpg", "resultat": "Crash", "zone": 1, "date": "19-12-2019", "heure": "14h:38m:55s"},{"frame": "valid152.jpg", "resultat": "Crash", "zone": 1, "date": "19-12-2019", "heure": "14h:38m:55s"},{"frame": "valid153.jpg", "resultat": "Without Crash", "zone": 1, "date": "19-12-2019", "heure": "14h:38m:55s"},{"frame": "valid154.jpg", "resultat": "Crash", "zone": 1, "date": "19-12-2019", "heure": "14h:38m:55s"},{"frame": "valid155.jpg", "resultat": "Without Crash", "zone": 1, "date": "19-12-2019", "heure": "14h:38m:55s"},{"frame": "valid156.jpg", "resultat": "Without Crash", "zone": 1, "date": "19-12-2019", "heure": "14h:38m:55s"},{"frame": "valid157.jpg", "resultat": "Crash", "zone": 1, "date": "19-12-2019", "heure": "14h:38m:55s"},{"frame": "valid158.jpg", "resultat": "Without Crash", "zone": 1, "date": "19-12-2019", "heure": "14h:38m:55s"},{"frame": "valid159.jpg", "resultat": "Without Crash", "zone": 1, "date": "19-12-2019", "heure": "14h:38m:55s"},{"frame": "valid16.jpg", "resultat": "Without Crash", "zone": 1, "date": "19-12-2019", "heure": "14h:38m:55s"},{"frame": "valid160.jpg", "resultat": "Without Crash", "zone": 1, "date": "19-12-2019", "heure": "14h:38m:55s"},{"frame": "valid161.jpg", "resultat": "Without Crash", "zone": 1, "date": "19-12-2019", "heure": "14h:38m:55s"},{"frame": "valid162.jpg", "resultat": "Crash", "zone": 1, "date": "19-12-2019", "heure": "14h:38m:55s"},{"frame": "valid163.jpg", "resultat": "Crash", "zone": 1, "date": "19-12-2019", "heure": "14h:38m:55s"},{"frame": "valid164.jpg", "resultat": "Crash", "zone": 1, "date": "19-12-2019", "heure": "14h:38m:55s"},{"frame": "valid165.jpg", "resultat": "Crash", "zone": 1, "date": "19-12-2019", "heure": "14h:38m:55s"},{"frame": "valid166.jpg", "resultat": "Crash", "zone": 1, "date": "19-12-2019", "heure": "14h:38m:55s"},{"frame": "valid167.jpg", "resultat": "Crash", "zone": 1, "date": "19-12-2019", "heure": "14h:38m:55s"},{"frame": "valid168.jpg", "resultat": "Crash", "zone": 1, "date": "19-12-2019", "heure": "14h:38m:55s"},{"frame": "valid169.jpg", "resultat": "Crash", "zone": 1, "date": "19-12-2019", "heure": "14h:38m:55s"},{"frame": "valid17.jpg", "resultat": "Crash", "zone": 1, "date": "19-12-2019", "heure": "14h:38m:55s"},{"frame": "valid170.jpg", "resultat": "Crash", "zone": 1, "date": "19-12-2019", "heure": "14h:38m:55s"},{"frame": "valid171.jpg", "resultat": "Crash", "zone": 1, "date": "19-12-2019", "heure": "14h:38m:55s"},{"frame": "valid172.jpg", "resultat": "Crash", "zone": 1, "date": "19-12-2019", "heure": "14h:38m:55s"},{"frame": "valid173.jpg", "resultat": "Crash", "zone": 1, "date": "19-12-2019", "heure": "14h:38m:55s"},{"frame": "valid174.jpg", "resultat": "Without Crash", "zone": 1, "date": "19-12-2019", "heure": "14h:38m:55s"},{"frame": "valid175.jpg", "resultat": "Crash", "zone": 1, "date": "19-12-2019", "heure": "14h:38m:55s"},{"frame": "valid176.jpg", "resultat": "Crash", "zone": 1, "date": "19-12-2019", "heure": "14h:38m:55s"},{"frame": "valid177.jpg", "resultat": "Crash", "zone": 1, "date": "19-12-2019", "heure": "14h:38m:55s"},{"frame": "valid178.jpg", "resultat": "Crash", "zone": 1, "date": "19-12-2019", "heure": "14h:38m:55s"},{"frame": "valid179.jpg", "resultat": "Crash", "zone": 1, "date": "19-12-2019", "heure": "14h:38m:55s"},{"frame": "valid18.jpg", "resultat": "Crash", "zone": 1, "date": "19-12-2019", "heure": "14h:38m:55s"},{"frame": "valid180.jpg", "resultat": "Crash", "zone": 1, "date": "19-12-2019", "heure": "14h:38m:55s"},{"frame": "valid181.jpg", "resultat": "Crash", "zone": 1, "date": "19-12-2019", "heure": "14h:38m:55s"},{"frame": "valid182.jpg", "resultat": "Crash", "zone": 1, "date": "19-12-2019", "heure": "14h:38m:55s"},{"frame": "valid183.jpg", "resultat": "Crash", "zone": 1, "date": "19-12-2019", "heure": "14h:38m:55s"},{"frame": "valid184.jpg", "resultat": "Crash", "zone": 1, "date": "19-12-2019", "heure": "14h:38m:55s"},{"frame": "valid185.jpg", "resultat": "Without Crash", "zone": 1, "date": "19-12-2019", "heure": "14h:38m:55s"},{"frame": "valid186.jpg", "resultat": "Without Crash", "zone": 1, "date": "19-12-2019", "heure": "14h:38m:55s"},{"frame": "valid187.jpg", "resultat": "Crash", "zone": 1, "date": "19-12-2019", "heure": "14h:38m:55s"},{"frame": "valid188.jpg", "resultat": "Crash", "zone": 1, "date": "19-12-2019", "heure": "14h:38m:55s"},{"frame": "valid189.jpg", "resultat": "Without Crash", "zone": 1, "date": "19-12-2019", "heure": "14h:38m:55s"},{"frame": "valid19.jpg", "resultat": "Crash", "zone": 1, "date": "19-12-2019", "heure": "14h:38m:55s"},{"frame": "valid190.jpg", "resultat": "Crash", "zone": 1, "date": "19-12-2019", "heure": "14h:38m:55s"},{"frame": "valid191.jpg", "resultat": "Without Crash", "zone": 1, "date": "19-12-2019", "heure": "14h:38m:55s"},{"frame": "valid192.jpg", "resultat": "Without Crash", "zone": 1, "date": "19-12-2019", "heure": "14h:38m:55s"},{"frame": "valid193.jpg", "resultat": "Without Crash", "zone": 1, "date": "19-12-2019", "heure": "14h:38m:55s"},{"frame": "valid194.jpg", "resultat": "Without Crash", "zone": 1, "date": "19-12-2019", "heure": "14h:38m:55s"},{"frame": "valid195.jpg", "resultat": "Without Crash", "zone": 1, "date": "19-12-2019", "heure": "14h:38m:55s"},{"frame": "valid196.jpg", "resultat": "Without Crash", "zone": 1, "date": "19-12-2019", "heure": "14h:38m:55s"},{"frame": "valid197.jpg", "resultat": "Without Crash", "zone": 1, "date": "19-12-2019", "heure": "14h:38m:55s"},{"frame": "valid198.jpg", "resultat": "Without Crash", "zone": 1, "date": "19-12-2019", "heure": "14h:38m:55s"},{"frame": "valid199.jpg", "resultat": "Crash", "zone": 1, "date": "19-12-2019", "heure": "14h:38m:55s"},{"frame": "valid2.jpg", "resultat": "Crash", "zone": 1, "date": "19-12-2019", "heure": "14h:38m:55s"},{"frame": "valid20.jpg", "resultat": "Crash", "zone": 1, "date": "19-12-2019", "heure": "14h:38m:55s"},{"frame": "valid200.jpg", "resultat": "Crash", "zone": 1, "date": "19-12-2019", "heure": "14h:38m:55s"},{"frame": "valid201.jpg", "resultat": "Without Crash", "zone": 1, "date": "19-12-2019", "heure": "14h:38m:55s"},{"frame": "valid202.jpg", "resultat": "Crash", "zone": 1, "date": "19-12-2019", "heure": "14h:38m:55s"},{"frame": "valid203.jpg", "resultat": "Crash", "zone": 1, "date": "19-12-2019", "heure": "14h:38m:55s"},{"frame": "valid204.jpg", "resultat": "Crash", "zone": 1, "date": "19-12-2019", "heure": "14h:38m:55s"},{"frame": "valid205.jpg", "resultat": "Crash", "zone": 1, "date": "19-12-2019", "heure": "14h:38m:55s"},{"frame": "valid206.jpg", "resultat": "Crash", "zone": 1, "date": "19-12-2019", "heure": "14h:38m:55s"},{"frame": "valid207.jpg", "resultat": "Crash", "zone": 1, "date": "19-12-2019", "heure": "14h:38m:55s"},{"frame": "valid208.jpg", "resultat": "Crash", "zone": 1, "date": "19-12-2019", "heure": "14h:38m:55s"},{"frame": "valid209.jpg", "resultat": "Crash", "zone": 1, "date": "19-12-2019", "heure": "14h:38m:55s"},{"frame": "valid21.jpg", "resultat": "Crash", "zone": 1, "date": "19-12-2019", "heure": "14h:38m:55s"},{"frame": "valid210.jpg", "resultat": "Crash", "zone": 1, "date": "19-12-2019", "heure": "14h:38m:55s"},{"frame": "valid211.jpg", "resultat": "Crash", "zone": 1, "date": "19-12-2019", "heure": "14h:38m:55s"},{"frame": "valid212.jpg", "resultat": "Without Crash", "zone": 1, "date": "19-12-2019", "heure": "14h:38m:55s"},{"frame": "valid213.jpg", "resultat": "Crash", "zone": 1, "date": "19-12-2019", "heure": "14h:38m:55s"},{"frame": "valid214.jpg", "resultat": "Crash", "zone": 1, "date": "19-12-2019", "heure": "14h:38m:55s"},{"frame": "valid215.jpg", "resultat": "Crash", "zone": 1, "date": "19-12-2019", "heure": "14h:38m:55s"},{"frame": "valid216.jpg", "resultat": "Without Crash", "zone": 1, "date": "19-12-2019", "heure": "14h:38m:55s"},{"frame": "valid217.jpg", "resultat": "Without Crash", "zone": 1, "date": "19-12-2019", "heure": "14h:38m:55s"},{"frame": "valid218.jpg", "resultat": "Without Crash", "zone": 1, "date": "19-12-2019", "heure": "14h:38m:55s"},{"frame": "valid219.jpg", "resultat": "Without Crash", "zone": 1, "date": "19-12-2019", "heure": "14h:38m:55s"},{"frame": "valid22.jpg", "resultat": "Crash", "zone": 1, "date": "19-12-2019", "heure": "14h:38m:55s"},{"frame": "valid220.jpg", "resultat": "Without Crash", "zone": 1, "date": "19-12-2019", "heure": "14h:38m:55s"},{"frame": "valid221.jpg", "resultat": "Without Crash", "zone": 1, "date": "19-12-2019", "heure": "14h:38m:55s"},{"frame": "valid222.jpg", "resultat": "Without Crash", "zone": 1, "date": "19-12-2019", "heure": "14h:38m:55s"},{"frame": "valid223.jpg", "resultat": "Without Crash", "zone": 1, "date": "19-12-2019", "heure": "14h:38m:55s"},{"frame": "valid224.jpg", "resultat": "Without Crash", "zone": 1, "date": "19-12-2019", "heure": "14h:38m:55s"},{"frame": "valid225.jpg", "resultat": "Crash", "zone": 1, "date": "19-12-2019", "heure": "14h:38m:55s"},{"frame": "valid226.jpg", "resultat": "Crash", "zone": 1, "date": "19-12-2019", "heure": "14h:38m:55s"},{"frame": "valid227.jpg", "resultat": "Crash", "zone": 1, "date": "19-12-2019", "heure": "14h:38m:55s"},{"frame": "valid228.jpg", "resultat": "Crash", "zone": 1, "date": "19-12-2019", "heure": "14h:38m:55s"},{"frame": "valid229.jpg", "resultat": "Crash", "zone": 1, "date": "19-12-2019", "heure": "14h:38m:55s"},{"frame": "valid23.jpg", "resultat": "Crash", "zone": 1, "date": "19-12-2019", "heure": "14h:38m:55s"},{"frame": "valid230.jpg", "resultat": "Crash", "zone": 1, "date": "19-12-2019", "heure": "14h:38m:55s"},{"frame": "valid231.jpg", "resultat": "Without Crash", "zone": 1, "date": "19-12-2019", "heure": "14h:38m:55s"},{"frame": "valid232.jpg", "resultat": "Crash", "zone": 1, "date": "19-12-2019", "heure": "14h:38m:55s"},{"frame": "valid233.jpg", "resultat": "Without Crash", "zone": 1, "date": "19-12-2019", "heure": "14h:38m:55s"},{"frame": "valid234.jpg", "resultat": "Crash", "zone": 1, "date": "19-12-2019", "heure": "14h:38m:55s"},{"frame": "valid235.jpg", "resultat": "Without Crash", "zone": 1, "date": "19-12-2019", "heure": "14h:38m:55s"},{"frame": "valid236.jpg", "resultat": "Without Crash", "zone": 1, "date": "19-12-2019", "heure": "14h:38m:55s"},{"frame": "valid237.jpg", "resultat": "Without Crash", "zone": 1, "date": "19-12-2019", "heure": "14h:38m:55s"},{"frame": "valid238.jpg", "resultat": "Crash", "zone": 1, "date": "19-12-2019", "heure": "14h:38m:55s"},{"frame": "valid239.jpg", "resultat": "Without Crash", "zone": 1, "date": "19-12-2019", "heure": "14h:38m:55s"},{"frame": "valid24.jpg", "resultat": "Crash", "zone": 1, "date": "19-12-2019", "heure": "14h:38m:55s"},{"frame": "valid240.jpg", "resultat": "Without Crash", "zone": 1, "date": "19-12-2019", "heure": "14h:38m:55s"},{"frame": "valid241.jpg", "resultat": "Crash", "zone": 1, "date": "19-12-2019", "heure": "14h:38m:55s"},{"frame": "valid242.jpg", "resultat": "Crash", "zone": 1, "date": "19-12-2019", "heure": "14h:38m:55s"},{"frame": "valid243.jpg", "resultat": "Crash", "zone": 1, "date": "19-12-2019", "heure": "14h:38m:55s"},{"frame": "valid244.jpg", "resultat": "Crash", "zone": 1, "date": "19-12-2019", "heure": "14h:38m:55s"},{"frame": "valid245.jpg", "resultat": "Crash", "zone": 1, "date": "19-12-2019", "heure": "14h:38m:55s"},{"frame": "valid246.jpg", "resultat": "Crash", "zone": 1, "date": "19-12-2019", "heure": "14h:38m:55s"},{"frame": "valid247.jpg", "resultat": "Without Crash", "zone": 1, "date": "19-12-2019", "heure": "14h:38m:55s"},{"frame": "valid248.jpg", "resultat": "Crash", "zone": 1, "date": "19-12-2019", "heure": "14h:38m:55s"},{"frame": "valid249.jpg", "resultat": "Crash", "zone": 1, "date": "19-12-2019", "heure": "14h:38m:55s"},{"frame": "valid25.jpg", "resultat": "Crash", "zone": 1, "date": "19-12-2019", "heure": "14h:38m:55s"},{"frame": "valid250.jpg", "resultat": "Crash", "zone": 1, "date": "19-12-2019", "heure": "14h:38m:55s"},{"frame": "valid251.jpg", "resultat": "Without Crash", "zone": 1, "date": "19-12-2019", "heure": "14h:38m:55s"},{"frame": "valid252.jpg", "resultat": "Without Crash", "zone": 1, "date": "19-12-2019", "heure": "14h:38m:55s"},{"frame": "valid253.jpg", "resultat": "Crash", "zone": 1, "date": "19-12-2019", "heure": "14h:38m:55s"},{"frame": "valid254.jpg", "resultat": "Crash", "zone": 1, "date": "19-12-2019", "heure": "14h:38m:55s"},{"frame": "valid255.jpg", "resultat": "Crash", "zone": 1, "date": "19-12-2019", "heure": "14h:38m:55s"},{"frame": "valid256.jpg", "resultat": "Crash", "zone": 1, "date": "19-12-2019", "heure": "14h:38m:55s"},{"frame": "valid257.jpg", "resultat": "Crash", "zone": 1, "date": "19-12-2019", "heure": "14h:38m:55s"},{"frame": "valid258.jpg", "resultat": "Crash", "zone": 1, "date": "19-12-2019", "heure": "14h:38m:55s"},{"frame": "valid259.jpg", "resultat": "Crash", "zone": 1, "date": "19-12-2019", "heure": "14h:38m:55s"},{"frame": "valid26.jpg", "resultat": "Without Crash", "zone": 1, "date": "19-12-2019", "heure": "14h:38m:55s"},{"frame": "valid260.jpg", "resultat": "Crash", "zone": 1, "date": "19-12-2019", "heure": "14h:38m:55s"},{"frame": "valid261.jpg", "resultat": "Crash", "zone": 1, "date": "19-12-2019", "heure": "14h:38m:55s"},{"frame": "valid262.jpg", "resultat": "Crash", "zone": 1, "date": "19-12-2019", "heure": "14h:38m:55s"},{"frame": "valid263.jpg", "resultat": "Crash", "zone": 1, "date": "19-12-2019", "heure": "14h:38m:55s"},{"frame": "valid264.jpg", "resultat": "Crash", "zone": 1, "date": "19-12-2019", "heure": "14h:38m:55s"},{"frame": "valid265.jpg", "resultat": "Without Crash", "zone": 1, "date": "19-12-2019", "heure": "14h:38m:55s"},{"frame": "valid266.jpg", "resultat": "Crash", "zone": 1, "date": "19-12-2019", "heure": "14h:38m:55s"},{"frame": "valid267.jpg", "resultat": "Crash", "zone": 1, "date": "19-12-2019", "heure": "14h:38m:55s"},{"frame": "valid268.jpg", "resultat": "Without Crash", "zone": 1, "date": "19-12-2019", "heure": "14h:38m:55s"},{"frame": "valid269.jpg", "resultat": "Without Crash", "zone": 1, "date": "19-12-2019", "heure": "14h:38m:55s"},{"frame": "valid27.jpg", "resultat": "Crash", "zone": 1, "date": "19-12-2019", "heure": "14h:38m:55s"},{"frame": "valid270.jpg", "resultat": "Crash", "zone": 1, "date": "19-12-2019", "heure": "14h:38m:55s"},{"frame": "valid271.jpg", "resultat": "Crash", "zone": 1, "date": "19-12-2019", "heure": "14h:38m:55s"},{"frame": "valid272.jpg", "resultat": "Crash", "zone": 1, "date": "19-12-2019", "heure": "14h:38m:55s"},{"frame": "valid273.jpg", "resultat": "Without Crash", "zone": 1, "date": "19-12-2019", "heure": "14h:38m:55s"},{"frame": "valid274.jpg", "resultat": "Crash", "zone": 1, "date": "19-12-2019", "heure": "14h:38m:55s"},{"frame": "valid275.jpg", "resultat": "Crash", "zone": 1, "date": "19-12-2019", "heure": "14h:38m:55s"},{"frame": "valid276.jpg", "resultat": "Crash", "zone": 1, "date": "19-12-2019", "heure": "14h:38m:55s"},{"frame": "valid277.jpg", "resultat": "Crash", "zone": 1, "date": "19-12-2019", "heure": "14h:38m:55s"},{"frame": "valid278.jpg", "resultat": "Without Crash", "zone": 1, "date": "19-12-2019", "heure": "14h:38m:55s"},{"frame": "valid279.jpg", "resultat": "Crash", "zone": 1, "date": "19-12-2019", "heure": "14h:38m:55s"},{"frame": "valid28.jpg", "resultat": "Crash", "zone": 1, "date": "19-12-2019", "heure": "14h:38m:55s"},{"frame": "valid280.jpg", "resultat": "Crash", "zone": 1, "date": "19-12-2019", "heure": "14h:38m:55s"},{"frame": "valid281.jpg", "resultat": "Crash", "zone": 1, "date": "19-12-2019", "heure": "14h:38m:55s"},{"frame": "valid282.jpg", "resultat": "Crash", "zone": 1, "date": "19-12-2019", "heure": "14h:38m:55s"},{"frame": "valid283.jpg", "resultat": "Crash", "zone": 1, "date": "19-12-2019", "heure": "14h:38m:55s"},{"frame": "valid284.jpg", "resultat": "Crash", "zone": 1, "date": "19-12-2019", "heure": "14h:38m:55s"},{"frame": "valid285.jpg", "resultat": "Crash", "zone": 1, "date": "19-12-2019", "heure": "14h:38m:55s"},{"frame": "valid286.jpg", "resultat": "Crash", "zone": 1, "date": "19-12-2019", "heure": "14h:38m:55s"},{"frame": "valid287.jpg", "resultat": "Crash", "zone": 1, "date": "19-12-2019", "heure": "14h:38m:55s"},{"frame": "valid288.jpg", "resultat": "Crash", "zone": 1, "date": "19-12-2019", "heure": "14h:38m:55s"},{"frame": "valid289.jpg", "resultat": "Crash", "zone": 1, "date": "19-12-2019", "heure": "14h:38m:55s"},{"frame": "valid29.jpg", "resultat": "Crash", "zone": 1, "date": "19-12-2019", "heure": "14h:38m:55s"},{"frame": "valid290.jpg", "resultat": "Crash", "zone": 1, "date": "19-12-2019", "heure": "14h:38m:55s"},{"frame": "valid291.jpg", "resultat": "Crash", "zone": 1, "date": "19-12-2019", "heure": "14h:38m:55s"},{"frame": "valid292.jpg", "resultat": "Crash", "zone": 1, "date": "19-12-2019", "heure": "14h:38m:55s"},{"frame": "valid293.jpg", "resultat": "Without Crash", "zone": 1, "date": "19-12-2019", "heure": "14h:38m:55s"},{"frame": "valid294.jpg", "resultat": "Crash", "zone": 1, "date": "19-12-2019", "heure": "14h:38m:55s"},{"frame": "valid295.jpg", "resultat": "Crash", "zone": 1, "date": "19-12-2019", "heure": "14h:38m:55s"},{"frame": "valid296.jpg", "resultat": "Crash", "zone": 1, "date": "19-12-2019", "heure": "14h:38m:55s"},{"frame": "valid297.jpg", "resultat": "Without Crash", "zone": 1, "date": "19-12-2019", "heure": "14h:38m:55s"},{"frame": "valid298.jpg", "resultat": "Crash", "zone": 1, "date": "19-12-2019", "heure": "14h:38m:55s"},{"frame": "valid299.jpg", "resultat": "Crash", "zone": 1, "date": "19-12-2019", "heure": "14h:38m:55s"},{"frame": "valid3.jpg", "resultat": "Crash", "zone": 1, "date": "19-12-2019", "heure": "14h:38m:55s"},{"frame": "valid30.jpg", "resultat": "Crash", "zone": 1, "date": "19-12-2019", "heure": "14h:38m:55s"},{"frame": "valid300.jpg", "resultat": "Crash", "zone": 1, "date": "19-12-2019", "heure": "14h:38m:55s"},{"frame": "valid301.jpg", "resultat": "Crash", "zone": 1, "date": "19-12-2019", "heure": "14h:38m:55s"},{"frame": "valid302.jpg", "resultat": "Without Crash", "zone": 1, "date": "19-12-2019", "heure": "14h:38m:55s"},{"frame": "valid303.jpg", "resultat": "Crash", "zone": 1, "date": "19-12-2019", "heure": "14h:38m:55s"},{"frame": "valid304.jpg", "resultat": "Crash", "zone": 1, "date": "19-12-2019", "heure": "14h:38m:55s"},{"frame": "valid305.jpg", "resultat": "Crash", "zone": 1, "date": "19-12-2019", "heure": "14h:38m:55s"},{"frame": "valid306.jpg", "resultat": "Crash", "zone": 1, "date": "19-12-2019", "heure": "14h:38m:55s"},{"frame": "valid307.jpg", "resultat": "Crash", "zone": 1, "date": "19-12-2019", "heure": "14h:38m:55s"},{"frame": "valid308.jpg", "resultat": "Without Crash", "zone": 1, "date": "19-12-2019", "heure": "14h:38m:55s"},{"frame": "valid309.jpg", "resultat": "Without Crash", "zone": 1, "date": "19-12-2019", "heure": "14h:38m:55s"},{"frame": "valid31.jpg", "resultat": "Crash", "zone": 1, "date": "19-12-2019", "heure": "14h:38m:55s"},{"frame": "valid310.jpg", "resultat": "Crash", "zone": 1, "date": "19-12-2019", "heure": "14h:38m:55s"},{"frame": "valid311.jpg", "resultat": "Crash", "zone": 1, "date": "19-12-2019", "heure": "14h:38m:55s"},{"frame": "valid312.jpg", "resultat": "Crash", "zone": 1, "date": "19-12-2019", "heure": "14h:38m:55s"},{"frame": "valid313.jpg", "resultat": "Crash", "zone": 1, "date": "19-12-2019", "heure": "14h:38m:55s"},{"frame": "valid314.jpg", "resultat": "Crash", "zone": 1, "date": "19-12-2019", "heure": "14h:38m:55s"},{"frame": "valid315.jpg", "resultat": "Crash", "zone": 1, "date": "19-12-2019", "heure": "14h:38m:55s"},{"frame": "valid316.jpg", "resultat": "Crash", "zone": 1, "date": "19-12-2019", "heure": "14h:38m:55s"},{"frame": "valid317.jpg", "resultat": "Crash", "zone": 1, "date": "19-12-2019", "heure": "14h:38m:55s"},{"frame": "valid318.jpg", "resultat": "Crash", "zone": 1, "date": "19-12-2019", "heure": "14h:38m:55s"},{"frame": "valid319.jpg", "resultat": "Crash", "zone": 1, "date": "19-12-2019", "heure": "14h:38m:55s"},{"frame": "valid32.jpg", "resultat": "Crash", "zone": 1, "date": "19-12-2019", "heure": "14h:38m:55s"},{"frame": "valid320.jpg", "resultat": "Crash", "zone": 1, "date": "19-12-2019", "heure": "14h:38m:55s"},{"frame": "valid321.jpg", "resultat": "Crash", "zone": 1, "date": "19-12-2019", "heure": "14h:38m:55s"},{"frame": "valid322.jpg", "resultat": "Crash", "zone": 1, "date": "19-12-2019", "heure": "14h:38m:55s"},{"frame": "valid323.jpg", "resultat": "Crash", "zone": 1, "date": "19-12-2019", "heure": "14h:38m:55s"},{"frame": "valid324.jpg", "resultat": "Crash", "zone": 1, "date": "19-12-2019", "heure": "14h:38m:55s"},{"frame": "valid325.jpg", "resultat": "Crash", "zone": 1, "date": "19-12-2019", "heure": "14h:38m:55s"},{"frame": "valid326.jpg", "resultat": "Crash", "zone": 1, "date": "19-12-2019", "heure": "14h:38m:55s"},{"frame": "valid327.jpg", "resultat": "Crash", "zone": 1, "date": "19-12-2019", "heure": "14h:38m:55s"},{"frame": "valid328.jpg", "resultat": "Crash", "zone": 1, "date": "19-12-2019", "heure": "14h:38m:55s"},{"frame": "valid329.jpg", "resultat": "Without Crash", "zone": 1, "date": "19-12-2019", "heure": "14h:38m:55s"},{"frame": "valid33.jpg", "resultat": "Crash", "zone": 1, "date": "19-12-2019", "heure": "14h:38m:55s"},{"frame": "valid330.jpg", "resultat": "Crash", "zone": 1, "date": "19-12-2019", "heure": "14h:38m:55s"},{"frame": "valid331.jpg", "resultat": "Crash", "zone": 1, "date": "19-12-2019", "heure": "14h:38m:55s"},{"frame": "valid332.jpg", "resultat": "Crash", "zone": 1, "date": "19-12-2019", "heure": "14h:38m:55s"},{"frame": "valid333.jpg", "resultat": "Crash", "zone": 1, "date": "19-12-2019", "heure": "14h:38m:55s"},{"frame": "valid334.jpg", "resultat": "Crash", "zone": 1, "date": "19-12-2019", "heure": "14h:38m:55s"},{"frame": "valid335.jpg", "resultat": "Crash", "zone": 1, "date": "19-12-2019", "heure": "14h:38m:55s"},{"frame": "valid336.jpg", "resultat": "Crash", "zone": 1, "date": "19-12-2019", "heure": "14h:38m:55s"},{"frame": "valid337.jpg", "resultat": "Crash", "zone": 1, "date": "19-12-2019", "heure": "14h:38m:55s"},{"frame": "valid338.jpg", "resultat": "Crash", "zone": 1, "date": "19-12-2019", "heure": "14h:38m:55s"},{"frame": "valid339.jpg", "resultat": "Crash", "zone": 1, "date": "19-12-2019", "heure": "14h:38m:55s"},{"frame": "valid34.jpg", "resultat": "Crash", "zone": 1, "date": "19-12-2019", "heure": "14h:38m:55s"},{"frame": "valid340.jpg", "resultat": "Crash", "zone": 1, "date": "19-12-2019", "heure": "14h:38m:55s"},{"frame": "valid341.jpg", "resultat": "Crash", "zone": 1, "date": "19-12-2019", "heure": "14h:38m:55s"},{"frame": "valid342.jpg", "resultat": "Crash", "zone": 1, "date": "19-12-2019", "heure": "14h:38m:55s"},{"frame": "valid343.jpg", "resultat": "Crash", "zone": 1, "date": "19-12-2019", "heure": "14h:38m:55s"},{"frame": "valid344.jpg", "resultat": "Crash", "zone": 1, "date": "19-12-2019", "heure": "14h:38m:55s"},{"frame": "valid345.jpg", "resultat": "Crash", "zone": 1, "date": "19-12-2019", "heure": "14h:38m:55s"},{"frame": "valid346.jpg", "resultat": "Crash", "zone": 1, "date": "19-12-2019", "heure": "14h:38m:55s"},{"frame": "valid347.jpg", "resultat": "Crash", "zone": 1, "date": "19-12-2019", "heure": "14h:38m:55s"},{"frame": "valid348.jpg", "resultat": "Crash", "zone": 1, "date": "19-12-2019", "heure": "14h:38m:55s"},{"frame": "valid349.jpg", "resultat": "Crash", "zone": 1, "date": "19-12-2019", "heure": "14h:38m:55s"},{"frame": "valid35.jpg", "resultat": "Crash", "zone": 1, "date": "19-12-2019", "heure": "14h:38m:55s"},{"frame": "valid350.jpg", "resultat": "Crash", "zone": 1, "date": "19-12-2019", "heure": "14h:38m:55s"},{"frame": "valid351.jpg", "resultat": "Crash", "zone": 1, "date": "19-12-2019", "heure": "14h:38m:55s"},{"frame": "valid352.jpg", "resultat": "Crash", "zone": 1, "date": "19-12-2019", "heure": "14h:38m:55s"},{"frame": "valid353.jpg", "resultat": "Crash", "zone": 1, "date": "19-12-2019", "heure": "14h:38m:55s"},{"frame": "valid354.jpg", "resultat": "Crash", "zone": 1, "date": "19-12-2019", "heure": "14h:38m:55s"},{"frame": "valid355.jpg", "resultat": "Crash", "zone": 1, "date": "19-12-2019", "heure": "14h:38m:55s"},{"frame": "valid356.jpg", "resultat": "Crash", "zone": 1, "date": "19-12-2019", "heure": "14h:38m:55s"},{"frame": "valid357.jpg", "resultat": "Without Crash", "zone": 1, "date": "19-12-2019", "heure": "14h:38m:55s"},{"frame": "valid358.jpg", "resultat": "Crash", "zone": 1, "date": "19-12-2019", "heure": "14h:38m:55s"},{"frame": "valid359.jpg", "resultat": "Crash", "zone": 1, "date": "19-12-2019", "heure": "14h:38m:55s"},{"frame": "valid36.jpg", "resultat": "Crash", "zone": 1, "date": "19-12-2019", "heure": "14h:38m:55s"},{"frame": "valid360.jpg", "resultat": "Crash", "zone": 1, "date": "19-12-2019", "heure": "14h:38m:55s"},{"frame": "valid361.jpg", "resultat": "Crash", "zone": 1, "date": "19-12-2019", "heure": "14h:38m:55s"},{"frame": "valid362.jpg", "resultat": "Crash", "zone": 1, "date": "19-12-2019", "heure": "14h:38m:55s"},{"frame": "valid363.jpg", "resultat": "Crash", "zone": 1, "date": "19-12-2019", "heure": "14h:38m:55s"},{"frame": "valid364.jpg", "resultat": "Crash", "zone": 1, "date": "19-12-2019", "heure": "14h:38m:55s"},{"frame": "valid365.jpg", "resultat": "Crash", "zone": 1, "date": "19-12-2019", "heure": "14h:38m:55s"},{"frame": "valid366.jpg", "resultat": "Crash", "zone": 1, "date": "19-12-2019", "heure": "14h:38m:55s"},{"frame": "valid367.jpg", "resultat": "Crash", "zone": 1, "date": "19-12-2019", "heure": "14h:38m:55s"},{"frame": "valid368.jpg", "resultat": "Crash", "zone": 1, "date": "19-12-2019", "heure": "14h:38m:55s"},{"frame": "valid369.jpg", "resultat": "Crash", "zone": 1, "date": "19-12-2019", "heure": "14h:38m:55s"},{"frame": "valid37.jpg", "resultat": "Crash", "zone": 1, "date": "19-12-2019", "heure": "14h:38m:55s"},{"frame": "valid370.jpg", "resultat": "Crash", "zone": 1, "date": "19-12-2019", "heure": "14h:38m:55s"},{"frame": "valid371.jpg", "resultat": "Crash", "zone": 1, "date": "19-12-2019", "heure": "14h:38m:55s"},{"frame": "valid372.jpg", "resultat": "Crash", "zone": 1, "date": "19-12-2019", "heure": "14h:38m:55s"},{"frame": "valid373.jpg", "resultat": "Crash", "zone": 1, "date": "19-12-2019", "heure": "14h:38m:55s"},{"frame": "valid374.jpg", "resultat": "Crash", "zone": 1, "date": "19-12-2019", "heure": "14h:38m:55s"},{"frame": "valid375.jpg", "resultat": "Crash", "zone": 1, "date": "19-12-2019", "heure": "14h:38m:55s"},{"frame": "valid376.jpg", "resultat": "Crash", "zone": 1, "date": "19-12-2019", "heure": "14h:38m:55s"},{"frame": "valid377.jpg", "resultat": "Crash", "zone": 1, "date": "19-12-2019", "heure": "14h:38m:55s"},{"frame": "valid378.jpg", "resultat": "Crash", "zone": 1, "date": "19-12-2019", "heure": "14h:38m:55s"},{"frame": "valid379.jpg", "resultat": "Crash", "zone": 1, "date": "19-12-2019", "heure": "14h:38m:55s"},{"frame": "valid38.jpg", "resultat": "Crash", "zone": 1, "date": "19-12-2019", "heure": "14h:38m:55s"},{"frame": "valid380.jpg", "resultat": "Crash", "zone": 1, "date": "19-12-2019", "heure": "14h:38m:55s"},{"frame": "valid381.jpg", "resultat": "Crash", "zone": 1, "date": "19-12-2019", "heure": "14h:38m:55s"},{"frame": "valid382.jpg", "resultat": "Crash", "zone": 1, "date": "19-12-2019", "heure": "14h:38m:55s"},{"frame": "valid383.jpg", "resultat": "Crash", "zone": 1, "date": "19-12-2019", "heure": "14h:38m:55s"},{"frame": "valid384.jpg", "resultat": "Crash", "zone": 1, "date": "19-12-2019", "heure": "14h:38m:55s"},{"frame": "valid385.jpg", "resultat": "Crash", "zone": 1, "date": "19-12-2019", "heure": "14h:38m:55s"},{"frame": "valid386.jpg", "resultat": "Crash", "zone": 1, "date": "19-12-2019", "heure": "14h:38m:55s"},{"frame": "valid387.jpg", "resultat": "Crash", "zone": 1, "date": "19-12-2019", "heure": "14h:38m:55s"},{"frame": "valid388.jpg", "resultat": "Crash", "zone": 1, "date": "19-12-2019", "heure": "14h:38m:55s"},{"frame": "valid389.jpg", "resultat": "Crash", "zone": 1, "date": "19-12-2019", "heure": "14h:38m:55s"},{"frame": "valid39.jpg", "resultat": "Crash", "zone": 1, "date": "19-12-2019", "heure": "14h:38m:55s"},{"frame": "valid390.jpg", "resultat": "Crash", "zone": 1, "date": "19-12-2019", "heure": "14h:38m:55s"},{"frame": "valid391.jpg", "resultat": "Crash", "zone": 1, "date": "19-12-2019", "heure": "14h:38m:55s"},{"frame": "valid392.jpg", "resultat": "Crash", "zone": 1, "date": "19-12-2019", "heure": "14h:38m:55s"},{"frame": "valid393.jpg", "resultat": "Crash", "zone": 1, "date": "19-12-2019", "heure": "14h:38m:55s"},{"frame": "valid394.jpg", "resultat": "Crash", "zone": 1, "date": "19-12-2019", "heure": "14h:38m:55s"},{"frame": "valid395.jpg", "resultat": "Crash", "zone": 1, "date": "19-12-2019", "heure": "14h:38m:55s"},{"frame": "valid396.jpg", "resultat": "Crash", "zone": 1, "date": "19-12-2019", "heure": "14h:38m:55s"},{"frame": "valid397.jpg", "resultat": "Crash", "zone": 1, "date": "19-12-2019", "heure": "14h:38m:55s"},{"frame": "valid398.jpg", "resultat": "Crash", "zone": 1, "date": "19-12-2019", "heure": "14h:38m:55s"},{"frame": "valid399.jpg", "resultat": "Crash", "zone": 1, "date": "19-12-2019", "heure": "14h:38m:55s"},{"frame": "valid4.jpg", "resultat": "Crash", "zone": 1, "date": "19-12-2019", "heure": "14h:38m:55s"},{"frame": "valid40.jpg", "resultat": "Crash", "zone": 1, "date": "19-12-2019", "heure": "14h:38m:55s"},{"frame": "valid400.jpg", "resultat": "Crash", "zone": 1, "date": "19-12-2019", "heure": "14h:38m:55s"},{"frame": "valid401.jpg", "resultat": "Crash", "zone": 1, "date": "19-12-2019", "heure": "14h:38m:55s"},{"frame": "valid402.jpg", "resultat": "Crash", "zone": 1, "date": "19-12-2019", "heure": "14h:38m:55s"},{"frame": "valid403.jpg", "resultat": "Crash", "zone": 1, "date": "19-12-2019", "heure": "14h:38m:55s"},{"frame": "valid404.jpg", "resultat": "Crash", "zone": 1, "date": "19-12-2019", "heure": "14h:38m:55s"},{"frame": "valid405.jpg", "resultat": "Crash", "zone": 1, "date": "19-12-2019", "heure": "14h:38m:55s"},{"frame": "valid406.jpg", "resultat": "Without Crash", "zone": 1, "date": "19-12-2019", "heure": "14h:38m:55s"},{"frame": "valid407.jpg", "resultat": "Crash", "zone": 1, "date": "19-12-2019", "heure": "14h:38m:55s"},{"frame": "valid408.jpg", "resultat": "Crash", "zone": 1, "date": "19-12-2019", "heure": "14h:38m:55s"},{"frame": "valid409.jpg", "resultat": "Crash", "zone": 1, "date": "19-12-2019", "heure": "14h:38m:55s"},{"frame": "valid41.jpg", "resultat": "Crash", "zone": 1, "date": "19-12-2019", "heure": "14h:38m:55s"},{"frame": "valid410.jpg", "resultat": "Crash", "zone": 1, "date": "19-12-2019", "heure": "14h:38m:55s"},{"frame": "valid411.jpg", "resultat": "Crash", "zone": 1, "date": "19-12-2019", "heure": "14h:38m:55s"},{"frame": "valid412.jpg", "resultat": "Crash", "zone": 1, "date": "19-12-2019", "heure": "14h:38m:55s"},{"frame": "valid413.jpg", "resultat": "Crash", "zone": 1, "date": "19-12-2019", "heure": "14h:38m:55s"},{"frame": "valid414.jpg", "resultat": "Without Crash", "zone": 1, "date": "19-12-2019", "heure": "14h:38m:55s"},{"frame": "valid415.jpg", "resultat": "Without Crash", "zone": 1, "date": "19-12-2019", "heure": "14h:38m:55s"},{"frame": "valid416.jpg", "resultat": "Crash", "zone": 1, "date": "19-12-2019", "heure": "14h:38m:55s"},{"frame": "valid417.jpg", "resultat": "Crash", "zone": 1, "date": "19-12-2019", "heure": "14h:38m:55s"},{"frame": "valid418.jpg", "resultat": "Crash", "zone": 1, "date": "19-12-2019", "heure": "14h:38m:55s"},{"frame": "valid419.jpg", "resultat": "Crash", "zone": 1, "date": "19-12-2019", "heure": "14h:38m:55s"},{"frame": "valid42.jpg", "resultat": "Crash", "zone": 1, "date": "19-12-2019", "heure": "14h:38m:55s"},{"frame": "valid420.jpg", "resultat": "Crash", "zone": 1, "date": "19-12-2019", "heure": "14h:38m:55s"},{"frame": "valid421.jpg", "resultat": "Crash", "zone": 1, "date": "19-12-2019", "heure": "14h:38m:55s"},{"frame": "valid422.jpg", "resultat": "Crash", "zone": 1, "date": "19-12-2019", "heure": "14h:38m:55s"},{"frame": "valid423.jpg", "resultat": "Crash", "zone": 1, "date": "19-12-2019", "heure": "14h:38m:55s"},{"frame": "valid424.jpg", "resultat": "Crash", "zone": 1, "date": "19-12-2019", "heure": "14h:38m:55s"},{"frame": "valid425.jpg", "resultat": "Crash", "zone": 1, "date": "19-12-2019", "heure": "14h:38m:55s"},{"frame": "valid426.jpg", "resultat": "Crash", "zone": 1, "date": "19-12-2019", "heure": "14h:38m:55s"},{"frame": "valid427.jpg", "resultat": "Crash", "zone": 1, "date": "19-12-2019", "heure": "14h:38m:55s"},{"frame": "valid428.jpg", "resultat": "Crash", "zone": 1, "date": "19-12-2019", "heure": "14h:38m:55s"},{"frame": "valid429.jpg", "resultat": "Crash", "zone": 1, "date": "19-12-2019", "heure": "14h:38m:55s"},{"frame": "valid43.jpg", "resultat": "Crash", "zone": 1, "date": "19-12-2019", "heure": "14h:38m:55s"},{"frame": "valid430.jpg", "resultat": "Crash", "zone": 1, "date": "19-12-2019", "heure": "14h:38m:55s"},{"frame": "valid431.jpg", "resultat": "Crash", "zone": 1, "date": "19-12-2019", "heure": "14h:38m:55s"},{"frame": "valid432.jpg", "resultat": "Crash", "zone": 1, "date": "19-12-2019", "heure": "14h:38m:55s"},{"frame": "valid433.jpg", "resultat": "Crash", "zone": 1, "date": "19-12-2019", "heure": "14h:38m:55s"},{"frame": "valid434.jpg", "resultat": "Crash", "zone": 1, "date": "19-12-2019", "heure": "14h:38m:55s"},{"frame": "valid435.jpg", "resultat": "Crash", "zone": 1, "date": "19-12-2019", "heure": "14h:38m:55s"},{"frame": "valid436.jpg", "resultat": "Crash", "zone": 1, "date": "19-12-2019", "heure": "14h:38m:55s"},{"frame": "valid437.jpg", "resultat": "Crash", "zone": 1, "date": "19-12-2019", "heure": "14h:38m:55s"},{"frame": "valid438.jpg", "resultat": "Crash", "zone": 1, "date": "19-12-2019", "heure": "14h:38m:55s"},{"frame": "valid439.jpg", "resultat": "Crash", "zone": 1, "date": "19-12-2019", "heure": "14h:38m:55s"},{"frame": "valid44.jpg", "resultat": "Crash", "zone": 1, "date": "19-12-2019", "heure": "14h:38m:55s"},{"frame": "valid440.jpg", "resultat": "Crash", "zone": 1, "date": "19-12-2019", "heure": "14h:38m:55s"},{"frame": "valid441.jpg", "resultat": "Crash", "zone": 1, "date": "19-12-2019", "heure": "14h:38m:55s"},{"frame": "valid442.jpg", "resultat": "Crash", "zone": 1, "date": "19-12-2019", "heure": "14h:38m:55s"},{"frame": "valid443.jpg", "resultat": "Crash", "zone": 1, "date": "19-12-2019", "heure": "14h:38m:55s"},{"frame": "valid444.jpg", "resultat": "Crash", "zone": 1, "date": "19-12-2019", "heure": "14h:38m:55s"},{"frame": "valid445.jpg", "resultat": "Crash", "zone": 1, "date": "19-12-2019", "heure": "14h:38m:55s"},{"frame": "valid446.jpg", "resultat": "Without Crash", "zone": 1, "date": "19-12-2019", "heure": "14h:38m:55s"},{"frame": "valid447.jpg", "resultat": "Crash", "zone": 1, "date": "19-12-2019", "heure": "14h:38m:55s"},{"frame": "valid448.jpg", "resultat": "Crash", "zone": 1, "date": "19-12-2019", "heure": "14h:38m:55s"},{"frame": "valid449.jpg", "resultat": "Crash", "zone": 1, "date": "19-12-2019", "heure": "14h:38m:55s"},{"frame": "valid45.jpg", "resultat": "Crash", "zone": 1, "date": "19-12-2019", "heure": "14h:38m:55s"},{"frame": "valid450.jpg", "resultat": "Without Crash", "zone": 1, "date": "19-12-2019", "heure": "14h:38m:55s"},{"frame": "valid451.jpg", "resultat": "Crash", "zone": 1, "date": "19-12-2019", "heure": "14h:38m:55s"},{"frame": "valid452.jpg", "resultat": "Crash", "zone": 1, "date": "19-12-2019", "heure": "14h:38m:55s"},{"frame": "valid453.jpg", "resultat": "Crash", "zone": 1, "date": "19-12-2019", "heure": "14h:38m:55s"},{"frame": "valid454.jpg", "resultat": "Crash", "zone": 1, "date": "19-12-2019", "heure": "14h:38m:55s"},{"frame": "valid455.jpg", "resultat": "Crash", "zone": 1, "date": "19-12-2019", "heure": "14h:38m:55s"},{"frame": "valid456.jpg", "resultat": "Crash", "zone": 1, "date": "19-12-2019", "heure": "14h:38m:55s"},{"frame": "valid457.jpg", "resultat": "Crash", "zone": 1, "date": "19-12-2019", "heure": "14h:38m:55s"},{"frame": "valid458.jpg", "resultat": "Crash", "zone": 1, "date": "19-12-2019", "heure": "14h:38m:55s"},{"frame": "valid459.jpg", "resultat": "Crash", "zone": 1, "date": "19-12-2019", "heure": "14h:38m:55s"},{"frame": "valid46.jpg", "resultat": "Crash", "zone": 1, "date": "19-12-2019", "heure": "14h:38m:55s"},{"frame": "valid460.jpg", "resultat": "Without Crash", "zone": 1, "date": "19-12-2019", "heure": "14h:38m:55s"},{"frame": "valid461.jpg", "resultat": "Crash", "zone": 1, "date": "19-12-2019", "heure": "14h:38m:55s"},{"frame": "valid462.jpg", "resultat": "Crash", "zone": 1, "date": "19-12-2019", "heure": "14h:38m:55s"},{"frame": "valid463.jpg", "resultat": "Crash", "zone": 1, "date": "19-12-2019", "heure": "14h:38m:55s"},{"frame": "valid464.jpg", "resultat": "Crash", "zone": 1, "date": "19-12-2019", "heure": "14h:38m:55s"},{"frame": "valid465.jpg", "resultat": "Crash", "zone": 1, "date": "19-12-2019", "heure": "14h:38m:55s"},{"frame": "valid466.jpg", "resultat": "Crash", "zone": 1, "date": "19-12-2019", "heure": "14h:38m:55s"},{"frame": "valid467.jpg", "resultat": "Crash", "zone": 1, "date": "19-12-2019", "heure": "14h:38m:55s"},{"frame": "valid468.jpg", "resultat": "Crash", "zone": 1, "date": "19-12-2019", "heure": "14h:38m:55s"},{"frame": "valid469.jpg", "resultat": "Crash", "zone": 1, "date": "19-12-2019", "heure": "14h:38m:55s"},{"frame": "valid47.jpg", "resultat": "Crash", "zone": 1, "date": "19-12-2019", "heure": "14h:38m:55s"},{"frame": "valid470.jpg", "resultat": "Crash", "zone": 1, "date": "19-12-2019", "heure": "14h:38m:55s"},{"frame": "valid471.jpg", "resultat": "Crash", "zone": 1, "date": "19-12-2019", "heure": "14h:38m:55s"},{"frame": "valid472.jpg", "resultat": "Crash", "zone": 1, "date": "19-12-2019", "heure": "14h:38m:55s"},{"frame": "valid473.jpg", "resultat": "Crash", "zone": 1, "date": "19-12-2019", "heure": "14h:38m:55s"},{"frame": "valid474.jpg", "resultat": "Crash", "zone": 1, "date": "19-12-2019", "heure": "14h:38m:55s"},{"frame": "valid475.jpg", "resultat": "Crash", "zone": 1, "date": "19-12-2019", "heure": "14h:38m:55s"},{"frame": "valid476.jpg", "resultat": "Crash", "zone": 1, "date": "19-12-2019", "heure": "14h:38m:55s"},{"frame": "valid477.jpg", "resultat": "Without Crash", "zone": 1, "date": "19-12-2019", "heure": "14h:38m:55s"},{"frame": "valid478.jpg", "resultat": "Without Crash", "zone": 1, "date": "19-12-2019", "heure": "14h:38m:55s"},{"frame": "valid479.jpg", "resultat": "Crash", "zone": 1, "date": "19-12-2019", "heure": "14h:38m:55s"},{"frame": "valid48.jpg", "resultat": "Crash", "zone": 1, "date": "19-12-2019", "heure": "14h:38m:55s"},{"frame": "valid480.jpg", "resultat": "Crash", "zone": 1, "date": "19-12-2019", "heure": "14h:38m:55s"},{"frame": "valid481.jpg", "resultat": "Crash", "zone": 1, "date": "19-12-2019", "heure": "14h:38m:55s"},{"frame": "valid482.jpg", "resultat": "Crash", "zone": 1, "date": "19-12-2019", "heure": "14h:38m:55s"},{"frame": "valid483.jpg", "resultat": "Crash", "zone": 1, "date": "19-12-2019", "heure": "14h:38m:55s"},{"frame": "valid484.jpg", "resultat": "Crash", "zone": 1, "date": "19-12-2019", "heure": "14h:38m:55s"},{"frame": "valid485.jpg", "resultat": "Crash", "zone": 1, "date": "19-12-2019", "heure": "14h:38m:55s"},{"frame": "valid486.jpg", "resultat": "Crash", "zone": 1, "date": "19-12-2019", "heure": "14h:38m:55s"},{"frame": "valid487.jpg", "resultat": "Crash", "zone": 1, "date": "19-12-2019", "heure": "14h:38m:55s"},{"frame": "valid488.jpg", "resultat": "Crash", "zone": 1, "date": "19-12-2019", "heure": "14h:38m:55s"},{"frame": "valid489.jpg", "resultat": "Crash", "zone": 1, "date": "19-12-2019", "heure": "14h:38m:55s"},{"frame": "valid49.jpg", "resultat": "Without Crash", "zone": 1, "date": "19-12-2019", "heure": "14h:38m:55s"},{"frame": "valid490.jpg", "resultat": "Crash", "zone": 1, "date": "19-12-2019", "heure": "14h:38m:55s"},{"frame": "valid491.jpg", "resultat": "Crash", "zone": 1, "date": "19-12-2019", "heure": "14h:38m:55s"},{"frame": "valid492.jpg", "resultat": "Crash", "zone": 1, "date": "19-12-2019", "heure": "14h:38m:55s"},{"frame": "valid493.jpg", "resultat": "Crash", "zone": 1, "date": "19-12-2019", "heure": "14h:38m:55s"},{"frame": "valid494.jpg", "resultat": "Without Crash", "zone": 1, "date": "19-12-2019", "heure": "14h:38m:55s"},{"frame": "valid495.jpg", "resultat": "Crash", "zone": 1, "date": "19-12-2019", "heure": "14h:38m:55s"},{"frame": "valid496.jpg", "resultat": "Without Crash", "zone": 1, "date": "19-12-2019", "heure": "14h:38m:55s"},{"frame": "valid497.jpg", "resultat": "Crash", "zone": 1, "date": "19-12-2019", "heure": "14h:38m:55s"},{"frame": "valid498.jpg", "resultat": "Crash", "zone": 1, "date": "19-12-2019", "heure": "14h:38m:55s"},{"frame": "valid499.jpg", "resultat": "Crash", "zone": 1, "date": "19-12-2019", "heure": "14h:38m:55s"},{"frame": "valid5.jpg", "resultat": "Crash", "zone": 1, "date": "19-12-2019", "heure": "14h:38m:55s"},{"frame": "valid50.jpg", "resultat": "Crash", "zone": 1, "date": "19-12-2019", "heure": "14h:38m:55s"},{"frame": "valid500.jpg", "resultat": "Crash", "zone": 1, "date": "19-12-2019", "heure": "14h:38m:55s"},{"frame": "valid501.jpg", "resultat": "Crash", "zone": 1, "date": "19-12-2019", "heure": "14h:38m:55s"},{"frame": "valid502.jpg", "resultat": "Crash", "zone": 1, "date": "19-12-2019", "heure": "14h:38m:55s"},{"frame": "valid503.jpg", "resultat": "Crash", "zone": 1, "date": "19-12-2019", "heure": "14h:38m:55s"},{"frame": "valid504.jpg", "resultat": "Crash", "zone": 1, "date": "19-12-2019", "heure": "14h:38m:55s"},{"frame": "valid505.jpg", "resultat": "Crash", "zone": 1, "date": "19-12-2019", "heure": "14h:38m:55s"},{"frame": "valid506.jpg", "resultat": "Crash", "zone": 1, "date": "19-12-2019", "heure": "14h:38m:55s"},{"frame": "valid507.jpg", "resultat": "Crash", "zone": 1, "date": "19-12-2019", "heure": "14h:38m:55s"},{"frame": "valid508.jpg", "resultat": "Crash", "zone": 1, "date": "19-12-2019", "heure": "14h:38m:55s"},{"frame": "valid509.jpg", "resultat": "Crash", "zone": 1, "date": "19-12-2019", "heure": "14h:38m:55s"},{"frame": "valid51.jpg", "resultat": "Crash", "zone": 1, "date": "19-12-2019", "heure": "14h:38m:55s"},{"frame": "valid510.jpg", "resultat": "Crash", "zone": 1, "date": "19-12-2019", "heure": "14h:38m:55s"},{"frame": "valid511.jpg", "resultat": "Without Crash", "zone": 1, "date": "19-12-2019", "heure": "14h:38m:55s"},{"frame": "valid512.jpg", "resultat": "Crash", "zone": 1, "date": "19-12-2019", "heure": "14h:38m:55s"},{"frame": "valid513.jpg", "resultat": "Crash", "zone": 1, "date": "19-12-2019", "heure": "14h:38m:55s"},{"frame": "valid514.jpg", "resultat": "Crash", "zone": 1, "date": "19-12-2019", "heure": "14h:38m:55s"},{"frame": "valid515.jpg", "resultat": "Without Crash", "zone": 1, "date": "19-12-2019", "heure": "14h:38m:55s"},{"frame": "valid516.jpg", "resultat": "Without Crash", "zone": 1, "date": "19-12-2019", "heure": "14h:38m:55s"},{"frame": "valid517.jpg", "resultat": "Without Crash", "zone": 1, "date": "19-12-2019", "heure": "14h:38m:55s"},{"frame": "valid518.jpg", "resultat": "Without Crash", "zone": 1, "date": "19-12-2019", "heure": "14h:38m:55s"},{"frame": "valid519.jpg", "resultat": "Without Crash", "zone": 1, "date": "19-12-2019", "heure": "14h:38m:55s"},{"frame": "valid52.jpg", "resultat": "Crash", "zone": 1, "date": "19-12-2019", "heure": "14h:38m:55s"},{"frame": "valid520.jpg", "resultat": "Without Crash", "zone": 1, "date": "19-12-2019", "heure": "14h:38m:55s"},{"frame": "valid521.jpg", "resultat": "Without Crash", "zone": 1, "date": "19-12-2019", "heure": "14h:38m:55s"},{"frame": "valid522.jpg", "resultat": "Without Crash", "zone": 1, "date": "19-12-2019", "heure": "14h:38m:55s"},{"frame": "valid523.jpg", "resultat": "Without Crash", "zone": 1, "date": "19-12-2019", "heure": "14h:38m:55s"},{"frame": "valid524.jpg", "resultat": "Without Crash", "zone": 1, "date": "19-12-2019", "heure": "14h:38m:55s"},{"frame": "valid525.jpg", "resultat": "Without Crash", "zone": 1, "date": "19-12-2019", "heure": "14h:38m:55s"},{"frame": "valid526.jpg", "resultat": "Without Crash", "zone": 1, "date": "19-12-2019", "heure": "14h:38m:55s"},{"frame": "valid527.jpg", "resultat": "Without Crash", "zone": 1, "date": "19-12-2019", "heure": "14h:38m:55s"},{"frame": "valid528.jpg", "resultat": "Without Crash", "zone": 1, "date": "19-12-2019", "heure": "14h:38m:55s"},{"frame": "valid529.jpg", "resultat": "Without Crash", "zone": 1, "date": "19-12-2019", "heure": "14h:38m:55s"},{"frame": "valid53.jpg", "resultat": "Crash", "zone": 1, "date": "19-12-2019", "heure": "14h:38m:55s"},{"frame": "valid530.jpg", "resultat": "Without Crash", "zone": 1, "date": "19-12-2019", "heure": "14h:38m:55s"},{"frame": "valid531.jpg", "resultat": "Without Crash", "zone": 1, "date": "19-12-2019", "heure": "14h:38m:55s"},{"frame": "valid532.jpg", "resultat": "Without Crash", "zone": 1, "date": "19-12-2019", "heure": "14h:38m:55s"},{"frame": "valid533.jpg", "resultat": "Without Crash", "zone": 1, "date": "19-12-2019", "heure": "14h:38m:55s"},{"frame": "valid534.jpg", "resultat": "Crash", "zone": 1, "date": "19-12-2019", "heure": "14h:38m:55s"},{"frame": "valid535.jpg", "resultat": "Crash", "zone": 1, "date": "19-12-2019", "heure": "14h:38m:55s"},{"frame": "valid536.jpg", "resultat": "Crash", "zone": 1, "date": "19-12-2019", "heure": "14h:38m:55s"},{"frame": "valid537.jpg", "resultat": "Crash", "zone": 1, "date": "19-12-2019", "heure": "14h:38m:55s"},{"frame": "valid538.jpg", "resultat": "Crash", "zone": 1, "date": "19-12-2019", "heure": "14h:38m:55s"},{"frame": "valid539.jpg", "resultat": "Crash", "zone": 1, "date": "19-12-2019", "heure": "14h:38m:55s"},{"frame": "valid54.jpg", "resultat": "Crash", "zone": 1, "date": "19-12-2019", "heure": "14h:38m:55s"},{"frame": "valid540.jpg", "resultat": "Crash", "zone": 1, "date": "19-12-2019", "heure": "14h:38m:55s"},{"frame": "valid541.jpg", "resultat": "Crash", "zone": 1, "date": "19-12-2019", "heure": "14h:38m:55s"},{"frame": "valid542.jpg", "resultat": "Crash", "zone": 1, "date": "19-12-2019", "heure": "14h:38m:55s"},{"frame": "valid543.jpg", "resultat": "Crash", "zone": 1, "date": "19-12-2019", "heure": "14h:38m:55s"},{"frame": "valid544.jpg", "resultat": "Crash", "zone": 1, "date": "19-12-2019", "heure": "14h:38m:55s"},{"frame": "valid545.jpg", "resultat": "Crash", "zone": 1, "date": "19-12-2019", "heure": "14h:38m:55s"},{"frame": "valid546.jpg", "resultat": "Crash", "zone": 1, "date": "19-12-2019", "heure": "14h:38m:55s"},{"frame": "valid547.jpg", "resultat": "Crash", "zone": 1, "date": "19-12-2019", "heure": "14h:38m:55s"},{"frame": "valid548.jpg", "resultat": "Crash", "zone": 1, "date": "19-12-2019", "heure": "14h:38m:55s"},{"frame": "valid549.jpg", "resultat": "Crash", "zone": 1, "date": "19-12-2019", "heure": "14h:38m:55s"},{"frame": "valid55.jpg", "resultat": "Crash", "zone": 1, "date": "19-12-2019", "heure": "14h:38m:55s"},{"frame": "valid550.jpg", "resultat": "Crash", "zone": 1, "date": "19-12-2019", "heure": "14h:38m:55s"},{"frame": "valid551.jpg", "resultat": "Crash", "zone": 1, "date": "19-12-2019", "heure": "14h:38m:55s"},{"frame": "valid552.jpg", "resultat": "Crash", "zone": 1, "date": "19-12-2019", "heure": "14h:38m:55s"},{"frame": "valid553.jpg", "resultat": "Crash", "zone": 1, "date": "19-12-2019", "heure": "14h:38m:55s"},{"frame": "valid554.jpg", "resultat": "Crash", "zone": 1, "date": "19-12-2019", "heure": "14h:38m:55s"},{"frame": "valid555.jpg", "resultat": "Crash", "zone": 1, "date": "19-12-2019", "heure": "14h:38m:55s"},{"frame": "valid556.jpg", "resultat": "Crash", "zone": 1, "date": "19-12-2019", "heure": "14h:38m:55s"},{"frame": "valid557.jpg", "resultat": "Crash", "zone": 1, "date": "19-12-2019", "heure": "14h:38m:55s"},{"frame": "valid558.jpg", "resultat": "Crash", "zone": 1, "date": "19-12-2019", "heure": "14h:38m:55s"},{"frame": "valid559.jpg", "resultat": "Crash", "zone": 1, "date": "19-12-2019", "heure": "14h:38m:55s"},{"frame": "valid56.jpg", "resultat": "Crash", "zone": 1, "date": "19-12-2019", "heure": "14h:38m:55s"},{"frame": "valid560.jpg", "resultat": "Crash", "zone": 1, "date": "19-12-2019", "heure": "14h:38m:55s"},{"frame": "valid561.jpg", "resultat": "Crash", "zone": 1, "date": "19-12-2019", "heure": "14h:38m:55s"},{"frame": "valid562.jpg", "resultat": "Crash", "zone": 1, "date": "19-12-2019", "heure": "14h:38m:55s"},{"frame": "valid563.jpg", "resultat": "Crash", "zone": 1, "date": "19-12-2019", "heure": "14h:38m:55s"},{"frame": "valid564.jpg", "resultat": "Crash", "zone": 1, "date": "19-12-2019", "heure": "14h:38m:55s"},{"frame": "valid565.jpg", "resultat": "Crash", "zone": 1, "date": "19-12-2019", "heure": "14h:38m:55s"},{"frame": "valid566.jpg", "resultat": "Crash", "zone": 1, "date": "19-12-2019", "heure": "14h:38m:55s"},{"frame": "valid567.jpg", "resultat": "Crash", "zone": 1, "date": "19-12-2019", "heure": "14h:38m:55s"},{"frame": "valid568.jpg", "resultat": "Crash", "zone": 1, "date": "19-12-2019", "heure": "14h:38m:55s"},{"frame": "valid569.jpg", "resultat": "Without Crash", "zone": 1, "date": "19-12-2019", "heure": "14h:38m:55s"},{"frame": "valid57.jpg", "resultat": "Crash", "zone": 1, "date": "19-12-2019", "heure": "14h:38m:55s"},{"frame": "valid570.jpg", "resultat": "Without Crash", "zone": 1, "date": "19-12-2019", "heure": "14h:38m:55s"},{"frame": "valid571.jpg", "resultat": "Without Crash", "zone": 1, "date": "19-12-2019", "heure": "14h:38m:55s"},{"frame": "valid572.jpg", "resultat": "Crash", "zone": 1, "date": "19-12-2019", "heure": "14h:38m:55s"},{"frame": "valid573.jpg", "resultat": "Crash", "zone": 1, "date": "19-12-2019", "heure": "14h:38m:55s"},{"frame": "valid574.jpg", "resultat": "Crash", "zone": 1, "date": "19-12-2019", "heure": "14h:38m:55s"},{"frame": "valid575.jpg", "resultat": "Crash", "zone": 1, "date": "19-12-2019", "heure": "14h:38m:55s"},{"frame": "valid576.jpg", "resultat": "Crash", "zone": 1, "date": "19-12-2019", "heure": "14h:38m:55s"},{"frame": "valid577.jpg", "resultat": "Crash", "zone": 1, "date": "19-12-2019", "heure": "14h:38m:55s"},{"frame": "valid578.jpg", "resultat": "Without Crash", "zone": 1, "date": "19-12-2019", "heure": "14h:38m:55s"},{"frame": "valid579.jpg", "resultat": "Without Crash", "zone": 1, "date": "19-12-2019", "heure": "14h:38m:55s"},{"frame": "valid58.jpg", "resultat": "Crash", "zone": 1, "date": "19-12-2019", "heure": "14h:38m:55s"},{"frame": "valid580.jpg", "resultat": "Crash", "zone": 1, "date": "19-12-2019", "heure": "14h:38m:55s"},{"frame": "valid581.jpg", "resultat": "Crash", "zone": 1, "date": "19-12-2019", "heure": "14h:38m:55s"},{"frame": "valid582.jpg", "resultat": "Without Crash", "zone": 1, "date": "19-12-2019", "heure": "14h:38m:55s"},{"frame": "valid583.jpg", "resultat": "Without Crash", "zone": 1, "date": "19-12-2019", "heure": "14h:38m:55s"},{"frame": "valid584.jpg", "resultat": "Without Crash", "zone": 1, "date": "19-12-2019", "heure": "14h:38m:55s"},{"frame": "valid585.jpg", "resultat": "Crash", "zone": 1, "date": "19-12-2019", "heure": "14h:38m:55s"},{"frame": "valid586.jpg", "resultat": "Without Crash", "zone": 1, "date": "19-12-2019", "heure": "14h:38m:55s"},{"frame": "valid587.jpg", "resultat": "Crash", "zone": 1, "date": "19-12-2019", "heure": "14h:38m:55s"},{"frame": "valid588.jpg", "resultat": "Without Crash", "zone": 1, "date": "19-12-2019", "heure": "14h:38m:55s"},{"frame": "valid589.jpg", "resultat": "Crash", "zone": 1, "date": "19-12-2019", "heure": "14h:38m:55s"},{"frame": "valid59.jpg", "resultat": "Crash", "zone": 1, "date": "19-12-2019", "heure": "14h:38m:55s"},{"frame": "valid590.jpg", "resultat": "Crash", "zone": 1, "date": "19-12-2019", "heure": "14h:38m:55s"},{"frame": "valid591.jpg", "resultat": "Without Crash", "zone": 1, "date": "19-12-2019", "heure": "14h:38m:55s"},{"frame": "valid592.jpg", "resultat": "Without Crash", "zone": 1, "date": "19-12-2019", "heure": "14h:38m:55s"},{"frame": "valid593.jpg", "resultat": "Crash", "zone": 1, "date": "19-12-2019", "heure": "14h:38m:55s"},{"frame": "valid594.jpg", "resultat": "Without Crash", "zone": 1, "date": "19-12-2019", "heure": "14h:38m:55s"},{"frame": "valid595.jpg", "resultat": "Crash", "zone": 1, "date": "19-12-2019", "heure": "14h:38m:55s"},{"frame": "valid596.jpg", "resultat": "Crash", "zone": 1, "date": "19-12-2019", "heure": "14h:38m:55s"},{"frame": "valid597.jpg", "resultat": "Without Crash", "zone": 1, "date": "19-12-2019", "heure": "14h:38m:55s"},{"frame": "valid598.jpg", "resultat": "Crash", "zone": 1, "date": "19-12-2019", "heure": "14h:38m:55s"},{"frame": "valid599.jpg", "resultat": "Crash", "zone": 1, "date": "19-12-2019", "heure": "14h:38m:55s"},{"frame": "valid6.jpg", "resultat": "Crash", "zone": 1, "date": "19-12-2019", "heure": "14h:38m:55s"},{"frame": "valid60.jpg", "resultat": "Crash", "zone": 1, "date": "19-12-2019", "heure": "14h:38m:55s"},{"frame": "valid600.jpg", "resultat": "Without Crash", "zone": 1, "date": "19-12-2019", "heure": "14h:38m:55s"},{"frame": "valid601.jpg", "resultat": "Crash", "zone": 1, "date": "19-12-2019", "heure": "14h:38m:55s"},{"frame": "valid61.jpg", "resultat": "Crash", "zone": 1, "date": "19-12-2019", "heure": "14h:38m:55s"},{"frame": "valid62.jpg", "resultat": "Crash", "zone": 1, "date": "19-12-2019", "heure": "14h:38m:55s"},{"frame": "valid63.jpg", "resultat": "Crash", "zone": 1, "date": "19-12-2019", "heure": "14h:38m:55s"},{"frame": "valid64.jpg", "resultat": "Crash", "zone": 1, "date": "19-12-2019", "heure": "14h:38m:55s"},{"frame": "valid65.jpg", "resultat": "Crash", "zone": 1, "date": "19-12-2019", "heure": "14h:38m:55s"},{"frame": "valid66.jpg", "resultat": "Crash", "zone": 1, "date": "19-12-2019", "heure": "14h:38m:55s"},{"frame": "valid67.jpg", "resultat": "Crash", "zone": 1, "date": "19-12-2019", "heure": "14h:38m:55s"},{"frame": "valid68.jpg", "resultat": "Crash", "zone": 1, "date": "19-12-2019", "heure": "14h:38m:55s"},{"frame": "valid69.jpg", "resultat": "Crash", "zone": 1, "date": "19-12-2019", "heure": "14h:38m:55s"},{"frame": "valid7.jpg", "resultat": "Crash", "zone": 1, "date": "19-12-2019", "heure": "14h:38m:55s"},{"frame": "valid70.jpg", "resultat": "Without Crash", "zone": 1, "date": "19-12-2019", "heure": "14h:38m:55s"},{"frame": "valid71.jpg", "resultat": "Crash", "zone": 1, "date": "19-12-2019", "heure": "14h:38m:55s"},{"frame": "valid72.jpg", "resultat": "Crash", "zone": 1, "date": "19-12-2019", "heure": "14h:38m:55s"},{"frame": "valid73.jpg", "resultat": "Crash", "zone": 1, "date": "19-12-2019", "heure": "14h:38m:55s"},{"frame": "valid74.jpg", "resultat": "Crash", "zone": 1, "date": "19-12-2019", "heure": "14h:38m:55s"},{"frame": "valid75.jpg", "resultat": "Crash", "zone": 1, "date": "19-12-2019", "heure": "14h:38m:55s"},{"frame": "valid76.jpg", "resultat": "Crash", "zone": 1, "date": "19-12-2019", "heure": "14h:38m:55s"},{"frame": "valid77.jpg", "resultat": "Crash", "zone": 1, "date": "19-12-2019", "heure": "14h:38m:55s"},{"frame": "valid78.jpg", "resultat": "Crash", "zone": 1, "date": "19-12-2019", "heure": "14h:38m:55s"},{"frame": "valid79.jpg", "resultat": "Crash", "zone": 1, "date": "19-12-2019", "heure": "14h:38m:55s"},{"frame": "valid8.jpg", "resultat": "Crash", "zone": 1, "date": "19-12-2019", "heure": "14h:38m:55s"},{"frame": "valid80.jpg", "resultat": "Crash", "zone": 1, "date": "19-12-2019", "heure": "14h:38m:55s"},{"frame": "valid81.jpg", "resultat": "Crash", "zone": 1, "date": "19-12-2019", "heure": "14h:38m:55s"},{"frame": "valid82.jpg", "resultat": "Crash", "zone": 1, "date": "19-12-2019", "heure": "14h:38m:55s"},{"frame": "valid83.jpg", "resultat": "Crash", "zone": 1, "date": "19-12-2019", "heure": "14h:38m:55s"},{"frame": "valid84.jpg", "resultat": "Crash", "zone": 1, "date": "19-12-2019", "heure": "14h:38m:55s"},{"frame": "valid85.jpg", "resultat": "Crash", "zone": 1, "date": "19-12-2019", "heure": "14h:38m:55s"},{"frame": "valid86.jpg", "resultat": "Crash", "zone": 1, "date": "19-12-2019", "heure": "14h:38m:55s"},{"frame": "valid87.jpg", "resultat": "Crash", "zone": 1, "date": "19-12-2019", "heure": "14h:38m:55s"},{"frame": "valid88.jpg", "resultat": "Crash", "zone": 1, "date": "19-12-2019", "heure": "14h:38m:55s"},{"frame": "valid89.jpg", "resultat": "Crash", "zone": 1, "date": "19-12-2019", "heure": "14h:38m:55s"},{"frame": "valid9.jpg", "resultat": "Crash", "zone": 1, "date": "19-12-2019", "heure": "14h:38m:55s"},{"frame": "valid90.jpg", "resultat": "Crash", "zone": 1, "date": "19-12-2019", "heure": "14h:38m:55s"},{"frame": "valid91.jpg", "resultat": "Crash", "zone": 1, "date": "19-12-2019", "heure": "14h:38m:55s"},{"frame": "valid92.jpg", "resultat": "Crash", "zone": 1, "date": "19-12-2019", "heure": "14h:38m:55s"},{"frame": "valid93.jpg", "resultat": "Crash", "zone": 1, "date": "19-12-2019", "heure": "14h:38m:55s"},{"frame": "valid94.jpg", "resultat": "Crash", "zone": 1, "date": "19-12-2019", "heure": "14h:38m:55s"},{"frame": "valid95.jpg", "resultat": "Crash", "zone": 1, "date": "19-12-2019", "heure": "14h:38m:55s"},{"frame": "valid96.jpg", "resultat": "Crash", "zone": 1, "date": "19-12-2019", "heure": "14h:38m:55s"},{"frame": "valid97.jpg", "resultat": "Crash", "zone": 1, "date": "19-12-2019", "heure": "14h:38m:55s"},{"frame": "valid98.jpg", "resultat": "Crash", "zone": 1, "date": "19-12-2019", "heure": "14h:38m:55s"},{"frame": "valid99.jpg", "resultat": "Crash", "zone": 1, "date": "19-12-2019", "heure": "14h:38m:55s"}]}